{
  "brand_name": "Breakout Beauty UK launches with",
  "matched_query": "UK beauty brand launch",
  "evidence_link": "https://news.google.com/rss/articles/CBMiYkFVX3lxTFBFZEVkZkp4czJEVTNCVWFLOGpQdHB1eUJWTThQUHFvS29kVGFiVm56ZkVEbHliYnFVdWFkVFRRclJ6NjNnT0NZeDJuWUZnQ1ptQkczRWJ5WlJ0YjR1OFR2UHBR?oc=5",
  "website": "",
  "news_mentions": [
    {
      "title": "Breakout Beauty UK launches with support from the Council - The British Beauty Council",
      "link": "https://news.google.com/rss/articles/CBMiYkFVX3lxTFBFZEVkZkp4czJEVTNCVWFLOGpQdHB1eUJWTThQUHFvS29kVGFiVm56ZkVEbHliYnFVdWFkVFRRclJ6NjNnT0NZeDJuWUZnQ1ptQkczRWJ5WlJ0YjR1OFR2UHBR?oc=5",
      "published": "Thu, 14 Aug 2025 07:00:00 GMT"
    }
  ],
  "contact": {
    "primary_email": "",
    "other_emails": [],
    "contact_form_url": "",
    "checked_pages": []
  },
  "site": {
    "pages": {},
    "fetched_pages": {},
    "change_flags": []
  },
  "generated_at": "2026-02-28T23:56:57.696820+00:00",
  "score": 6,
  "score_reasons": [
    "1 news mention(s)"
  ],
  "has_contact": false
}